saludos_y_despedidas_espanol/__init__.py
saludos_y_despedidas_espanol/despedidas/__init__.py
saludos_y_despedidas_espanol/despedidas/despedidas.py
saludos_y_despedidas_espanol/saludos/__init__.py
saludos_y_despedidas_espanol/saludos/saludos.py
saludos_y_despedidas_espanol/saludos/preguntas_cortesia/__init__.py
saludos_y_despedidas_espanol/saludos/preguntas_cortesia/cortesias.py
demo_generacion_libreria-0.0.4.dist-info/METADATA
demo_generacion_libreria-0.0.4.dist-info/WHEEL
demo_generacion_libreria-0.0.4.dist-info/top_level.txt
demo_generacion_libreria-0.0.4.dist-info/RECORD
