Metadata-Version: 2.1
Name: demo-generacion-libreria
Version: 0.0.4
Summary: Module to show how to create a library
Home-page: UNKNOWN
Author: Pablo Suana
Author-email: pablo.suana@luceit.es
License: UNKNOWN
Platform: UNKNOWN
Classifier: Programming Language :: Python :: 3.6
Classifier: License :: OSI Approved :: MIT License
Classifier: Operating System :: OS Independent
Requires-Dist: pandas
